{
  "projectName": "PetSoft Tycoon",
  "version": "1.0.0",
  "lastUpdated": "2025-08-13T00:00:00Z",
  "phases": {
    "00-analysis": {
      "name": "Analysis - Requirements Analysis and Architecture Overview",
      "status": "not_started",
      "estimatedHours": 40,
      "actualHours": 0,
      "startDate": null,
      "endDate": null,
      "tasks": {
        "requirements_decomposition": {
          "name": "Requirements Decomposition",
          "status": "not_started",
          "estimatedHours": 5,
          "actualHours": 0,
          "subtasks": [
            "Extract core game loop",
            "Define unlock progression",
            "Map resource flow"
          ]
        },
        "feature_boundary_analysis": {
          "name": "Feature Boundary Analysis",
          "status": "not_started",
          "estimatedHours": 3,
          "actualHours": 0,
          "subtasks": [
            "Define feature boundaries",
            "Create dependencies matrix",
            "Validate independence"
          ]
        },
        "event_driven_architecture": {
          "name": "Event-Driven Architecture Design",
          "status": "not_started",
          "estimatedHours": 7,
          "actualHours": 0,
          "subtasks": [
            "Define event schema",
            "Design service contracts",
            "Create event bus interface"
          ]
        },
        "architecture_patterns": {
          "name": "Architecture Patterns",
          "status": "not_started",
          "estimatedHours": 5,
          "actualHours": 0,
          "subtasks": [
            "Vertical slice structure",
            "Legend-State integration",
            "Service implementation pattern"
          ]
        },
        "development_environment": {
          "name": "Development Environment Setup",
          "status": "not_started",
          "estimatedHours": 5,
          "actualHours": 0,
          "subtasks": [
            "Tool configuration",
            "Architecture documentation",
            "Development conventions"
          ]
        },
        "development_conventions": {
          "name": "Development Conventions",
          "status": "not_started",
          "estimatedHours": 3,
          "actualHours": 0,
          "subtasks": [
            "Code standards",
            "Testing strategy",
            "Validation checklist"
          ]
        }
      },
      "deliverables": [
        "Feature boundary map with dependencies",
        "Event schema with all event types defined",
        "Service contracts for each major feature",
        "Architecture Decision Records created",
        "Development environment verified"
      ]
    },
    "01-foundation": {
      "name": "Foundation - Project Setup, Dependencies, Configuration",
      "status": "not_started",
      "estimatedHours": 40,
      "actualHours": 0,
      "startDate": null,
      "endDate": null,
      "tasks": {
        "project_initialization": {
          "name": "Project Initialization",
          "status": "not_started",
          "estimatedHours": 1.5,
          "actualHours": 0,
          "subtasks": [
            "Create Expo project",
            "Install core dependencies",
            "Project configuration"
          ]
        },
        "core_infrastructure": {
          "name": "Core Infrastructure Implementation",
          "status": "not_started",
          "estimatedHours": 4.5,
          "actualHours": 0,
          "subtasks": [
            "EventBus implementation",
            "Result type implementation",
            "Legend-State integration"
          ]
        },
        "feature_folder_structure": {
          "name": "Feature Folder Structure",
          "status": "not_started",
          "estimatedHours": 3.5,
          "actualHours": 0,
          "subtasks": [
            "Create folder structure",
            "Feature index templates",
            "Service base templates"
          ]
        },
        "basic_save_system": {
          "name": "Basic Save System",
          "status": "not_started",
          "estimatedHours": 2,
          "actualHours": 0,
          "subtasks": [
            "Persistence service implementation",
            "Save/load testing"
          ]
        },
        "development_workflow": {
          "name": "Development Workflow",
          "status": "not_started",
          "estimatedHours": 1.5,
          "actualHours": 0,
          "subtasks": [
            "Hot reload setup",
            "Basic app integration"
          ]
        }
      },
      "deliverables": [
        "Expo SDK 53 project created and running",
        "Legend-State v3 beta installed and configured",
        "EventBus implementation complete and tested",
        "Feature folder structure created",
        "Save/load system functional"
      ]
    },
    "02-core-features": {
      "name": "Core Features - Game Loop, Clicking, Currency",
      "status": "not_started",
      "estimatedHours": 40,
      "actualHours": 0,
      "startDate": null,
      "endDate": null,
      "tasks": {
        "clicking_mechanics": {
          "name": "Clicking Mechanics Implementation",
          "status": "not_started",
          "estimatedHours": 4,
          "actualHours": 0,
          "subtasks": [
            "Core clicking service",
            "Click button component",
            "Number popup animations"
          ]
        },
        "currency_system": {
          "name": "Currency System Implementation",
          "status": "not_started",
          "estimatedHours": 4,
          "actualHours": 0,
          "subtasks": [
            "Currency service",
            "Currency display component",
            "Resource conversion logic"
          ]
        },
        "employee_system": {
          "name": "Employee System Implementation",
          "status": "not_started",
          "estimatedHours": 5,
          "actualHours": 0,
          "subtasks": [
            "Employee service",
            "Development department component",
            "Hire button component"
          ]
        },
        "game_loop_integration": {
          "name": "Game Loop Integration",
          "status": "not_started",
          "estimatedHours": 3,
          "actualHours": 0,
          "subtasks": [
            "Main game screen",
            "App.tsx update",
            "Service integration"
          ]
        }
      },
      "deliverables": [
        "Responsive click button with <50ms response time",
        "Resource management for lines, features, revenue",
        "Development department with 4 employee types",
        "Complete flow from click → resources → employees → automation"
      ]
    },
    "03-integration": {
      "name": "Integration - Department Systems and Upgrades",
      "status": "not_started",
      "estimatedHours": 80,
      "actualHours": 0,
      "startDate": null,
      "endDate": null,
      "tasks": {
        "sales_department": {
          "name": "Sales Department Implementation",
          "status": "not_started",
          "estimatedHours": 5,
          "actualHours": 0,
          "subtasks": [
            "Sales service",
            "Sales department component",
            "Lead generation mechanics"
          ]
        },
        "customer_experience_department": {
          "name": "Customer Experience Department",
          "status": "not_started",
          "estimatedHours": 3,
          "actualHours": 0,
          "subtasks": [
            "Customer experience service",
            "Ticket resolution system",
            "Satisfaction multipliers"
          ]
        },
        "upgrade_system": {
          "name": "Upgrade System Implementation",
          "status": "not_started",
          "estimatedHours": 6,
          "actualHours": 0,
          "subtasks": [
            "Upgrade service",
            "Upgrade definitions",
            "Prerequisite system"
          ]
        },
        "manager_automation": {
          "name": "Manager Automation System",
          "status": "not_started",
          "estimatedHours": 3,
          "actualHours": 0,
          "subtasks": [
            "Manager service",
            "Auto-purchase logic",
            "Manager UI components"
          ]
        },
        "integration_testing": {
          "name": "Integration and Testing",
          "status": "not_started",
          "estimatedHours": 3,
          "actualHours": 0,
          "subtasks": [
            "Updated game screen",
            "Navigation setup",
            "Integration testing"
          ]
        }
      },
      "deliverables": [
        "Sales department with lead generation and revenue conversion",
        "Customer Experience department with ticket resolution",
        "Comprehensive upgrade definitions with prerequisites",
        "Manager hiring system with tier progression",
        "Tabbed navigation between game sections"
      ]
    },
    "04-quality": {
      "name": "Quality - Polish, Performance Optimization, Testing",
      "status": "not_started",
      "estimatedHours": 40,
      "actualHours": 0,
      "startDate": null,
      "endDate": null,
      "tasks": {
        "performance_optimization": {
          "name": "Performance Optimization",
          "status": "not_started",
          "estimatedHours": 4.5,
          "actualHours": 0,
          "subtasks": [
            "Performance monitoring setup",
            "EventBus optimization",
            "State update optimization"
          ]
        },
        "audio_system": {
          "name": "Audio System Implementation",
          "status": "not_started",
          "estimatedHours": 2.5,
          "actualHours": 0,
          "subtasks": [
            "Audio service",
            "Audio assets setup",
            "Dynamic sound effects"
          ]
        },
        "remaining_departments": {
          "name": "Remaining Departments Implementation",
          "status": "not_started",
          "estimatedHours": 5,
          "actualHours": 0,
          "subtasks": [
            "Product department",
            "Design department",
            "QA department"
          ]
        },
        "testing_implementation": {
          "name": "Testing Implementation",
          "status": "not_started",
          "estimatedHours": 3.5,
          "actualHours": 0,
          "subtasks": [
            "Unit testing setup",
            "Integration testing",
            "Test coverage reports"
          ]
        },
        "prestige_system": {
          "name": "Prestige System Foundation",
          "status": "not_started",
          "estimatedHours": 2,
          "actualHours": 0,
          "subtasks": [
            "Prestige service implementation",
            "IP calculation and bonuses",
            "Game reset mechanics"
          ]
        }
      },
      "deliverables": [
        "Consistent 60fps performance on target devices",
        "Dynamic audio system with 7 core sound types",
        "All 7 departments fully implemented",
        "Comprehensive unit test suite",
        "Basic prestige system functional"
      ]
    },
    "05-deployment": {
      "name": "Deployment - Build, Release, and Launch",
      "status": "not_started",
      "estimatedHours": 40,
      "actualHours": 0,
      "startDate": null,
      "endDate": null,
      "tasks": {
        "production_build": {
          "name": "Production Build Configuration",
          "status": "not_started",
          "estimatedHours": 3,
          "actualHours": 0,
          "subtasks": [
            "Build optimization",
            "Performance validation",
            "Bundle size optimization"
          ]
        },
        "analytics_crash_reporting": {
          "name": "Analytics and Crash Reporting",
          "status": "not_started",
          "estimatedHours": 3,
          "actualHours": 0,
          "subtasks": [
            "Analytics implementation",
            "Crash reporting setup",
            "Error tracking service"
          ]
        },
        "app_store_preparation": {
          "name": "App Store Preparation",
          "status": "not_started",
          "estimatedHours": 3,
          "actualHours": 0,
          "subtasks": [
            "App store assets",
            "Store metadata setup",
            "Privacy policy creation"
          ]
        },
        "build_submission": {
          "name": "Build and Submission",
          "status": "not_started",
          "estimatedHours": 4,
          "actualHours": 0,
          "subtasks": [
            "Production builds",
            "App store submission",
            "Review process management"
          ]
        },
        "launch_monitoring": {
          "name": "Launch and Monitoring",
          "status": "not_started",
          "estimatedHours": 3,
          "actualHours": 0,
          "subtasks": [
            "Pre-launch checklist",
            "Launch execution",
            "Post-launch monitoring"
          ]
        }
      },
      "deliverables": [
        "Optimized production builds for iOS and Android",
        "User analytics tracking implemented",
        "iOS App Store listing complete with all assets",
        "Successful submission to both app stores",
        "Launch monitoring dashboard operational"
      ]
    }
  },
  "overallProgress": {
    "tasksCompleted": 0,
    "totalTasks": 28,
    "percentComplete": 0,
    "estimatedTotalHours": 280,
    "actualTotalHours": 0
  },
  "milestones": [
    {
      "name": "Architecture Foundation Complete",
      "targetDate": "2025-08-20",
      "dependencies": ["00-analysis", "01-foundation"],
      "status": "pending"
    },
    {
      "name": "Core Game Loop Functional",
      "targetDate": "2025-08-27",
      "dependencies": ["02-core-features"],
      "status": "pending"
    },
    {
      "name": "All Departments Integrated",
      "targetDate": "2025-09-10",
      "dependencies": ["03-integration"],
      "status": "pending"
    },
    {
      "name": "Production Ready",
      "targetDate": "2025-09-17",
      "dependencies": ["04-quality"],
      "status": "pending"
    },
    {
      "name": "App Store Launch",
      "targetDate": "2025-09-24",
      "dependencies": ["05-deployment"],
      "status": "pending"
    }
  ],
  "riskItems": [
    {
      "id": "R-001",
      "title": "Progression Balance",
      "severity": "high",
      "status": "open",
      "mitigation": "Extensive playtesting, configurable balance parameters"
    },
    {
      "id": "R-002", 
      "title": "Performance on Low-End Devices",
      "severity": "high",
      "status": "open",
      "mitigation": "Early performance testing, optimization sprints"
    },
    {
      "id": "R-003",
      "title": "Save Data Corruption",
      "severity": "high", 
      "status": "open",
      "mitigation": "Multiple save slots, data validation, recovery mechanisms"
    }
  ],
  "notes": [
    "Project follows vertical slicing architecture with Legend-State v3 beta",
    "All features communicate via EventBus - no direct cross-feature imports allowed",
    "Target performance: 60fps, <100MB RAM, <3s load time",
    "Success metrics: 30%+ 7-day retention, 15+ min average session"
  ]
}